pds.sumo_tools-0.2.6-py3.9-nspkg.pth
pds/sumo_mgr/VERSION.txt
pds/sumo_mgr/__init__.py
pds/sumo_mgr/generate.py
pds/sumo_mgr/util.py
pds/sumo_mgr/validate.py
pds.sumo_tools-0.2.6.dist-info/LICENSE.md
pds.sumo_tools-0.2.6.dist-info/METADATA
pds.sumo_tools-0.2.6.dist-info/NOTICE.txt
pds.sumo_tools-0.2.6.dist-info/WHEEL
pds.sumo_tools-0.2.6.dist-info/entry_points.txt
pds.sumo_tools-0.2.6.dist-info/namespace_packages.txt
pds.sumo_tools-0.2.6.dist-info/top_level.txt
pds.sumo_tools-0.2.6.dist-info/zip-safe
pds.sumo_tools-0.2.6.dist-info/RECORD
